{"StartTimes":{"0":0,"2147483647":70,"1":0,"2":15,"3":49,"4":51,"5":52,"6":57,"7":24,"8":61,"9":62,"10":64,"11":70,"12":0,"13":30,"14":32,"15":37,"16":43,"17":10,"18":48,"19":54,"20":56,"21":62,"22":0,"23":6,"24":42,"25":52,"26":57,"27":63,"28":21,"29":23,"30":43,"31":54,"32":60,"33":64,"34":1,"35":5,"36":15,"37":31,"38":55,"39":2,"40":4,"41":12,"42":18,"43":30,"44":0,"45":8,"46":23,"47":29,"48":51,"49":63,"50":0,"51":4,"52":10,"53":29,"54":36,"55":57},"CompletionTimes":{"0":0,"2147483647":71,"1":5,"2":20,"3":51,"4":52,"5":53,"6":63,"7":30,"8":62,"9":64,"10":70,"11":71,"12":6,"13":32,"14":37,"15":43,"16":48,"17":15,"18":54,"19":55,"20":61,"21":66,"22":3,"23":12,"24":48,"25":57,"26":63,"27":69,"28":23,"29":25,"30":49,"31":60,"32":61,"33":67,"34":2,"35":8,"36":21,"37":37,"38":56,"39":4,"40":8,"41":18,"42":24,"43":36,"44":1,"45":9,"46":29,"47":31,"48":57,"49":69,"50":4,"51":10,"52":15,"53":30,"54":42,"55":60},"MachineAssignment":{"1":{"Id":1},"50":{"Id":3},"44":{"Id":6},"34":{"Id":6},"39":{"Id":6},"51":{"Id":6},"17":{"Id":6},"35":{"Id":1},"36":{"Id":6},"45":{"Id":1},"40":{"Id":3},"28":{"Id":6},"52":{"Id":3},"46":{"Id":6},"53":{"Id":6},"29":{"Id":1},"47":{"Id":1},"37":{"Id":1},"22":{"Id":5},"12":{"Id":2},"23":{"Id":2},"13":{"Id":6},"14":{"Id":6},"41":{"Id":2},"42":{"Id":2},"15":{"Id":6},"7":{"Id":2},"30":{"Id":6},"2":{"Id":3},"16":{"Id":5},"3":{"Id":6},"4":{"Id":1},"48":{"Id":6},"5":{"Id":3},"6":{"Id":6},"43":{"Id":2},"54":{"Id":2},"24":{"Id":2},"25":{"Id":1},"26":{"Id":4},"55":{"Id":1},"49":{"Id":4},"27":{"Id":6},"18":{"Id":2},"31":{"Id":2},"19":{"Id":3},"32":{"Id":1},"38":{"Id":3},"20":{"Id":3},"8":{"Id":3},"9":{"Id":1},"21":{"Id":3},"33":{"Id":1},"10":{"Id":2},"11":{"Id":1},"2147483647":{"Id":2}},"Watch":{"IsRunning":false,"Elapsed":"00:00:01.7952186","ElapsedMilliseconds":1795,"ElapsedTicks":1795218679},"Makespan":71}
