{"StartTimes":{"26":0,"21":0,"22":10,"1":0,"23":20,"27":10,"28":21,"29":32,"11":10,"31":10,"12":21,"2":10,"3":23,"4":35,"41":0,"42":14,"43":27,"44":38,"45":49,"24":31,"25":48,"30":59,"32":22,"5":47,"16":14,"17":32,"18":42,"19":52,"20":74,"13":31,"14":48,"15":62,"33":40,"34":57,"35":72,"36":21,"37":39,"38":49,"39":61,"46":32,"47":47,"48":62,"49":72,"50":84,"6":10,"7":30,"8":48,"9":62,"10":85,"40":72},"CompletionTimes":{"26":10,"21":10,"22":20,"1":10,"23":31,"27":21,"28":32,"29":43,"11":21,"31":22,"12":31,"2":23,"3":35,"4":47,"41":14,"42":27,"43":38,"44":49,"45":59,"24":48,"25":62,"30":74,"32":40,"5":63,"16":32,"17":42,"18":52,"19":65,"20":85,"13":48,"14":58,"15":72,"33":57,"34":72,"35":84,"36":39,"37":49,"38":61,"39":71,"46":47,"47":62,"48":72,"49":82,"50":94,"6":30,"7":48,"8":62,"9":76,"10":97,"40":93},"MachineAssignment":{"1":{"Id":1},"6":{"Id":1},"41":{"Id":2},"16":{"Id":2},"46":{"Id":2},"21":{"Id":3},"11":{"Id":3},"36":{"Id":3},"26":{"Id":4},"31":{"Id":4},"43":{"Id":5},"33":{"Id":5},"27":{"Id":6},"13":{"Id":6},"42":{"Id":7},"2":{"Id":8},"18":{"Id":8},"44":{"Id":9},"49":{"Id":10},"17":{"Id":11},"39":{"Id":13},"22":{"Id":15},"29":{"Id":15},"48":{"Id":15},"24":{"Id":17},"23":{"Id":18},"9":{"Id":19},"38":{"Id":21},"34":{"Id":22},"12":{"Id":23},"37":{"Id":24},"3":{"Id":25},"14":{"Id":25},"7":{"Id":27},"32":{"Id":28},"8":{"Id":29},"28":{"Id":31},"19":{"Id":33},"47":{"Id":34},"4":{"Id":36},"25":{"Id":37},"15":{"Id":37},"40":{"Id":37},"5":{"Id":38},"45":{"Id":39},"30":{"Id":39},"20":{"Id":39},"10":{"Id":39},"35":{"Id":40},"50":{"Id":40}},"Watch":{"IsRunning":false,"Elapsed":"00:00:00.2576751","ElapsedMilliseconds":257,"ElapsedTicks":257675185},"Makespan":97}
