{"StartTimes":{"1":87,"2":234,"3":460,"4":145,"5":295,"6":361,"7":145,"8":210,"9":315,"10":0,"11":87,"12":315,"13":0,"14":145,"15":210,"16":0,"17":295,"18":418},"CompletionTimes":{"1":234,"2":357,"3":610,"4":295,"5":361,"6":511,"7":207,"8":315,"9":415,"10":87,"11":260,"12":460,"13":145,"14":210,"15":295,"16":145,"17":418,"18":538},"MachineAssignment":{"10":{"Id":1},"1":{"Id":1},"2":{"Id":1},"16":{"Id":2},"7":{"Id":2},"5":{"Id":2},"13":{"Id":3},"4":{"Id":3},"17":{"Id":3},"14":{"Id":4},"8":{"Id":4},"12":{"Id":4},"3":{"Id":4},"11":{"Id":5},"9":{"Id":5},"18":{"Id":5},"15":{"Id":6},"6":{"Id":7}},"Watch":{"IsRunning":false,"Elapsed":"00:00:00.0687625","ElapsedMilliseconds":68,"ElapsedTicks":68762528},"Makespan":610}
