{"StartTimes":{"0":0,"2147483647":622,"1":0,"2":147,"3":342,"4":275,"5":489,"6":555,"7":0,"8":62,"9":242,"10":62,"11":242,"12":492,"13":147,"14":304,"15":369,"16":0,"17":154,"18":502},"CompletionTimes":{"0":0,"2147483647":637,"1":147,"2":277,"3":502,"4":489,"5":555,"6":650,"7":62,"8":242,"9":342,"10":127,"11":492,"12":637,"13":275,"14":369,"15":454,"16":154,"17":304,"18":622},"MachineAssignment":{"1":{"Id":1},"7":{"Id":2},"10":{"Id":2},"8":{"Id":3},"13":{"Id":1},"4":{"Id":1},"2":{"Id":2},"11":{"Id":3},"16":{"Id":4},"5":{"Id":2},"17":{"Id":4},"14":{"Id":4},"12":{"Id":4},"9":{"Id":5},"3":{"Id":5},"18":{"Id":5},"15":{"Id":6},"6":{"Id":6},"2147483647":{"Id":5}},"Watch":{"IsRunning":false,"Elapsed":"00:00:00.0397892","ElapsedMilliseconds":39,"ElapsedTicks":39789227},"Makespan":637}
