{"StartTimes":{"1":0,"2":100,"3":350,"4":527,"5":215,"6":429,"7":672,"8":767,"9":0,"10":245,"11":435,"12":563,"13":0,"14":262,"15":500,"16":968,"17":87,"18":215,"19":262,"20":347,"21":65,"22":210,"23":333,"24":513,"25":333,"26":478,"27":803,"28":948,"29":0,"30":535,"31":803,"32":968},"CompletionTimes":{"1":100,"2":223,"3":500,"4":672,"5":429,"6":495,"7":767,"8":917,"9":87,"10":350,"11":535,"12":728,"13":65,"14":435,"15":645,"16":1138,"17":215,"18":262,"19":347,"20":527,"21":210,"22":333,"23":513,"24":563,"25":478,"26":602,"27":948,"28":1088,"29":245,"30":803,"31":968,"32":1118},"MachineAssignment":{"9":{"Id":1},"17":{"Id":1},"5":{"Id":1},"13":{"Id":2},"21":{"Id":2},"6":{"Id":2},"1":{"Id":3},"22":{"Id":3},"25":{"Id":3},"26":{"Id":3},"29":{"Id":4},"10":{"Id":4},"3":{"Id":4},"15":{"Id":4},"18":{"Id":5},"14":{"Id":5},"11":{"Id":5},"30":{"Id":5},"27":{"Id":5},"28":{"Id":5},"19":{"Id":6},"20":{"Id":6},"4":{"Id":6},"7":{"Id":6},"31":{"Id":6},"16":{"Id":6},"2":{"Id":7},"23":{"Id":7},"24":{"Id":7},"12":{"Id":7},"8":{"Id":7},"32":{"Id":7}},"Watch":{"IsRunning":false,"Elapsed":"00:00:00.0604359","ElapsedMilliseconds":60,"ElapsedTicks":60435980},"Makespan":1138}
