{"StartTimes":{"36":0,"41":0,"16":18,"1":0,"2":14,"17":29,"42":25,"31":14,"21":13,"6":0,"37":18,"7":11,"38":32,"39":43,"26":31,"3":42,"22":23,"23":36,"32":31,"24":54,"25":65,"18":42,"11":50,"4":54,"43":75,"19":57,"27":50,"12":64,"28":70,"13":80,"20":72,"33":41,"29":80,"8":60,"34":76,"14":101,"46":23,"47":43,"5":75,"48":59,"35":99,"9":80,"49":72,"44":94,"45":105,"10":96,"50":100,"30":125,"40":111,"15":130},"CompletionTimes":{"36":18,"41":13,"16":29,"1":14,"2":25,"17":42,"42":38,"31":31,"21":23,"6":11,"37":32,"7":21,"38":43,"39":70,"26":50,"3":54,"22":36,"23":49,"32":41,"24":65,"25":75,"18":57,"11":64,"4":75,"43":91,"19":72,"27":60,"12":80,"28":80,"13":101,"20":87,"33":66,"29":94,"8":76,"34":99,"14":112,"46":42,"47":59,"5":96,"48":69,"35":110,"9":94,"49":100,"44":105,"45":125,"10":111,"50":118,"30":140,"40":130,"15":152},"MachineAssignment":{"41":{"Id":1},"21":{"Id":1},"46":{"Id":1},"36":{"Id":2},"16":{"Id":2},"1":{"Id":3},"31":{"Id":3},"26":{"Id":3},"11":{"Id":3},"6":{"Id":4},"19":{"Id":5},"49":{"Id":5},"7":{"Id":6},"39":{"Id":6},"28":{"Id":6},"9":{"Id":6},"2":{"Id":7},"42":{"Id":7},"18":{"Id":7},"12":{"Id":8},"29":{"Id":8},"44":{"Id":8},"4":{"Id":9},"43":{"Id":9},"17":{"Id":10},"3":{"Id":10},"24":{"Id":10},"22":{"Id":11},"23":{"Id":11},"13":{"Id":11},"33":{"Id":12},"14":{"Id":12},"32":{"Id":13},"48":{"Id":13},"37":{"Id":14},"38":{"Id":15},"47":{"Id":15},"27":{"Id":16},"8":{"Id":16},"34":{"Id":16},"35":{"Id":17},"20":{"Id":18},"50":{"Id":18},"45":{"Id":19},"30":{"Id":19},"25":{"Id":20},"5":{"Id":20},"10":{"Id":20},"40":{"Id":20},"15":{"Id":20}},"Watch":{"IsRunning":false,"Elapsed":"00:00:00.3312602","ElapsedMilliseconds":331,"ElapsedTicks":331260268},"Makespan":152}
